{
  "results": [
    {
      "category": "content",
      "keyword": "british history",
      "latest_score": 77,
      "recent_avg": 41.3,
      "previous_avg": 16.7,
      "rise_percent": 148.0,
      "viral_score": 80.2,
      "question": "Is British History being ignored in modern Britain? Yes or No?",
      "caption": "\ud83c\uddec\ud83c\udde7 Is British History being ignored in modern Britain? Yes or No? Let us know in the comments! #britain #english #patriotic #uk",
      "product": "British history books"
    }
  ],
  "emerging": [],
  "last_updated": "2026-06-08 10:31:37"
}